metis_agent/__init__.py
metis_agent/__main__.py
metis_agent/simple_test.py
metis_agent/assets/__init__.py
metis_agent/assets/base.py
metis_agent/assets/compositions.py
metis_agent/assets/instructions.py
metis_agent/assets/modes.py
metis_agent/assets/personas.py
metis_agent/assets/skills.py
metis_agent/assets/workflows.py
metis_agent/auth/__init__.py
metis_agent/auth/api_key_manager.py
metis_agent/auth/credentials.py
metis_agent/auth/secure_storage.py
metis_agent/blueprints/__init__.py
metis_agent/blueprints/core/__init__.py
metis_agent/blueprints/core/blueprint.py
metis_agent/blueprints/core/builder.py
metis_agent/blueprints/core/engine.py
metis_agent/blueprints/core/registry.py
metis_agent/cli/__init__.py
metis_agent/cli/agent_commands.py
metis_agent/cli/assets_commands.py
metis_agent/cli/cache_commands.py
metis_agent/cli/code_commands.py
metis_agent/cli/code_commands_new.py
metis_agent/cli/commands.py
metis_agent/cli/conversational_agent.py
metis_agent/cli/deps_commands.py
metis_agent/cli/enhanced_input.py
metis_agent/cli/enhanced_streaming_interface.py
metis_agent/cli/enhanced_todo_integration.py
metis_agent/cli/file_commands.py
metis_agent/cli/git_commands.py
metis_agent/cli/interactive_commands.py
metis_agent/cli/knowledge_commands.py
metis_agent/cli/natural_todo_workflow.py
metis_agent/cli/phase3_commands.py
metis_agent/cli/phase4_commands.py
metis_agent/cli/progress_display.py
metis_agent/cli/progress_streamer.py
metis_agent/cli/project_commands.py
metis_agent/cli/project_manager.py
metis_agent/cli/status_manager.py
metis_agent/cli/streaming_interface.py
metis_agent/cli/todo_commands.py
metis_agent/cli/unified_streaming.py
metis_agent/cli/refactored/__init__.py
metis_agent/cli/refactored/command_router.py
metis_agent/cli/refactored/interface_adapters.py
metis_agent/cli/refactored/project_handlers.py
metis_agent/cli/refactored/request_processors.py
metis_agent/cli/refactored/session_managers.py
metis_agent/cli/refactored/streaming_handlers.py
metis_agent-0.20.0.dist-info/licenses/LICENSE
metis_agent-0.20.0.dist-info/METADATA
metis_agent-0.20.0.dist-info/WHEEL
metis_agent-0.20.0.dist-info/entry_points.txt
metis_agent-0.20.0.dist-info/top_level.txt
metis_agent-0.20.0.dist-info/RECORD
