Metadata-Version: 2.4
Name: metis-agent
Version: 0.20.0
Summary: Production-ready AI agent framework with comprehensive testing, intelligent caching, connection pooling, unified interfaces, 36+ tools, and enterprise-grade security - 30-50% cost savings through smart optimization
Home-page: https://github.com/metisos/metisos_agentV1
Author: Metis OS Team
Author-email: cjohnson@metisos.com
License: Apache License 2.0
Project-URL: Documentation, https://github.com/metisos/metisos_agentV1/blob/main/DOCUMENTATION.md
Project-URL: Bug Tracker, https://github.com/metisos/metisos_agentV1/issues
Project-URL: Source Code, https://github.com/metisos/metisos_agentV1
Keywords: ai,agent,llm,composable-assets,personas,instructions,workflows,skills,asset-composition,openai,groq,anthropic,huggingface,ollama,local-models,transformers,tools,memory,conversation,context-management,token-aware,intelligent-summarization,blueprint-detection,autonomous-tools,dynamic-generation,capability-expansion,text-analysis,sentiment-analysis,web-scraping,python-execution,advanced-math,nlp,readability-assessment,e2b,code-sandbox,secure-execution,cloud-sandbox,privacy,offline,quantiz
Classifier: Development Status :: 5 - Production/Stable
Classifier: Intended Audience :: Developers
Classifier: Topic :: Software Development :: Libraries :: Python Modules
Classifier: Topic :: Scientific/Engineering :: Artificial Intelligence
Classifier: Programming Language :: Python :: 3
Classifier: Programming Language :: Python :: 3.8
Classifier: Programming Language :: Python :: 3.9
Classifier: Programming Language :: Python :: 3.10
Classifier: Programming Language :: Python :: 3.11
Classifier: License :: OSI Approved :: Apache Software License
Classifier: Operating System :: OS Independent
Classifier: Topic :: Security
Classifier: Topic :: Security :: Cryptography
Requires-Python: >=3.8
License-File: LICENSE
Requires-Dist: openai>=1.0.0
Requires-Dist: groq>=0.4.0
Requires-Dist: anthropic>=0.5.0
Requires-Dist: huggingface-hub>=0.16.0
Requires-Dist: flask>=2.0.0
Requires-Dist: flask-cors>=3.0.0
Requires-Dist: requests>=2.25.0
Requires-Dist: python-dotenv>=0.15.0
Requires-Dist: click>=8.0.0
Requires-Dist: numpy>=1.20.0
Requires-Dist: cryptography>=41.0.0
Requires-Dist: pydantic>=1.8.0
Requires-Dist: beautifulsoup4>=4.9.0
Requires-Dist: lxml>=4.6.0
Requires-Dist: scipy>=1.7.0
Requires-Dist: sympy>=1.8
Requires-Dist: e2b-code-interpreter>=1.5.0
Requires-Dist: PyYAML>=5.4.0
Requires-Dist: tabulate>=0.8.0
Requires-Dist: networkx>=2.8.0
Requires-Dist: scikit-learn>=1.0.0
Requires-Dist: rich>=10.0.0
Requires-Dist: psutil>=5.8.0
Requires-Dist: prompt-toolkit>=3.0.0
Requires-Dist: asyncio>=3.4.0
Requires-Dist: pytest>=6.0.0
Requires-Dist: pytest-cov>=2.12.0
Provides-Extra: dev
Requires-Dist: pytest>=6.0.0; extra == "dev"
Requires-Dist: pytest-cov>=2.12.0; extra == "dev"
Requires-Dist: black>=21.5b2; extra == "dev"
Requires-Dist: isort>=5.9.1; extra == "dev"
Requires-Dist: flake8>=3.9.2; extra == "dev"
Requires-Dist: mypy>=0.812; extra == "dev"
Provides-Extra: docs
Requires-Dist: sphinx>=4.0.0; extra == "docs"
Requires-Dist: sphinx-rtd-theme>=0.5.2; extra == "docs"
Requires-Dist: myst-parser>=0.15.1; extra == "docs"
Provides-Extra: local-models
Requires-Dist: transformers>=4.20.0; extra == "local-models"
Requires-Dist: torch>=1.12.0; extra == "local-models"
Requires-Dist: requests>=2.25.0; extra == "local-models"
Provides-Extra: security
Requires-Dist: cryptography>=41.0.0; extra == "security"
Requires-Dist: psutil>=5.8.0; extra == "security"
Requires-Dist: pyotp>=2.6.0; extra == "security"
Dynamic: author
Dynamic: author-email
Dynamic: classifier
Dynamic: description
Dynamic: description-content-type
Dynamic: home-page
Dynamic: keywords
Dynamic: license
Dynamic: license-file
Dynamic: project-url
Dynamic: provides-extra
Dynamic: requires-dist
Dynamic: requires-python
Dynamic: summary
